ua_djangolibrary/__init__.py
ua_djangolibrary/guardedsettings.py
ua_djangolibrary/projectbuilder.py
ua_djangolibrary-0.6.6.dist-info/entry_points.txt
ua_djangolibrary-0.6.6.dist-info/LICENSE
ua_djangolibrary-0.6.6.dist-info/WHEEL
ua_djangolibrary-0.6.6.dist-info/METADATA
ua_djangolibrary-0.6.6.dist-info/RECORD
