Metadata-Version: 2.1
Name: ua_djangolibrary
Version: 0.6.6
Summary: Includes the guardedsettings.py and projectbuilder.py modules under Apache 2.0 LICENSE. 
Author-email: Gunnar Swan <gunnar.swan@yahoo.com>
Requires-Python: >=3.6
